omgtools/__init__.py
omgtools/basics/__init__.py
omgtools/basics/geometry.py
omgtools/basics/optilayer.py
omgtools/basics/shape.py
omgtools/basics/spline.py
omgtools/basics/spline_extra.py
omgtools/environment/__init__.py
omgtools/environment/environment.py
omgtools/environment/frame.py
omgtools/environment/obstacle.py
omgtools/execution/__init__.py
omgtools/execution/deployer.py
omgtools/execution/plotlayer.py
omgtools/execution/simulator.py
omgtools/export/__init__.py
omgtools/export/export.py
omgtools/export/export_admm.py
omgtools/export/export_formation.py
omgtools/export/export_p2p.py
omgtools/export/export_rendezvous.py
omgtools/export/point2point/Makefile
omgtools/export/point2point/Point2Point.cpp
omgtools/export/point2point/Point2Point.hpp
omgtools/export/point2point/example.cpp
omgtools/export/point2point/instructions.txt
omgtools/export/point2point/admm/ADMMPoint2Point.cpp
omgtools/export/point2point/admm/ADMMPoint2Point.hpp
omgtools/export/point2point/admm/formation/FormationPoint2Point.cpp
omgtools/export/point2point/admm/formation/FormationPoint2Point.hpp
omgtools/export/point2point/admm/rendezvous/RendezVous.cpp
omgtools/export/point2point/admm/rendezvous/RendezVous.hpp
omgtools/export/tests/formation/test.cpp
omgtools/export/tests/point2point/test.cpp
omgtools/export/tests/rendezvous/test.cpp
omgtools/export/vehicles/Holonomic.cpp
omgtools/export/vehicles/Holonomic.hpp
omgtools/export/vehicles/Vehicle.cpp
omgtools/export/vehicles/Vehicle.hpp
omgtools/gui/__init__.py
omgtools/gui/gcode_block.py
omgtools/gui/gcode_reader.py
omgtools/gui/gui.py
omgtools/gui/svg_reader.py
omgtools/problems/__init__.py
omgtools/problems/admm.py
omgtools/problems/distributedproblem.py
omgtools/problems/dualdecomposition.py
omgtools/problems/dualmethod.py
omgtools/problems/formation.py
omgtools/problems/formation_central.py
omgtools/problems/formation_dualdec.py
omgtools/problems/gcodeproblem.py
omgtools/problems/gcodeschedulerproblem.py
omgtools/problems/globalplanner.py
omg_tools-0.1.4.dist-info/LICENSE
omg_tools-0.1.4.dist-info/METADATA
omg_tools-0.1.4.dist-info/WHEEL
omg_tools-0.1.4.dist-info/top_level.txt
omg_tools-0.1.4.dist-info/RECORD
